{"noiseKey":{"private":{"type":"Buffer","data":"6PGC0p6mzQykIPFgotCLnCCYeEO1iCNBbGjXHeXUw08="},"public":{"type":"Buffer","data":"Hr7LUJmCIlnDwkMAuO3Gz8VkRIxX+OZErRbli1OS70g="}},"pairingEphemeralKeyPair":{"private":{"type":"Buffer","data":"cFdJ+ZF6wwI6/c/7cH49DxgSinEisVHaPy/gTPjo/kk="},"public":{"type":"Buffer","data":"kl7eZUBrq9hJVU/J+oX8UaLFN7KW56yehvVpWqn+Tgg="}},"signedIdentityKey":{"private":{"type":"Buffer","data":"kFFU9qrcNSIJV8pERIKv1mjVss53a3XdYC3g8bkjQGE="},"public":{"type":"Buffer","data":"7LMhObB2dYaV389VVkrvV87AOYOdH6E66WYnFl5oFQU="}},"signedPreKey":{"keyPair":{"private":{"type":"Buffer","data":"8FFhtF633A9hkWu31bUZbxrOJildJUGD8x4eacH0pkM="},"public":{"type":"Buffer","data":"OHcLT4CMLHOL6+P7f8qkE95dP5rM02DnW/LVkpnpdiE="}},"signature":{"type":"Buffer","data":"4lEfuXy3Du/nvii0vbYLlXQcz8tOsabOvOrdphTt654HLQcbFYZdPkRR+KSC99pPMWhRy50gay6CEx75/Odbhw=="},"keyId":1},"registrationId":40,"advSecretKey":"fJHJcX+UNLaVn51MsmfrlwMOPLDzi5kFrzqvqdRtYK4=","processedHistoryMessages":[{"key":{"remoteJid":"557183158563@s.whatsapp.net","fromMe":false,"id":"3ABC1ADDA20CBC3E1E5E","participant":"","addressingMode":"pn"},"messageTimestamp":1771543354},{"key":{"remoteJid":"557183158563@s.whatsapp.net","fromMe":false,"id":"3AAD8E73D6FF32BF68A4","participant":"","addressingMode":"pn"},"messageTimestamp":1771543356},{"key":{"remoteJid":"557183158563@s.whatsapp.net","fromMe":false,"id":"3AAC3FB318A1842E1265","participant":"","addressingMode":"pn"},"messageTimestamp":1771543376},{"key":{"remoteJid":"557183158563@s.whatsapp.net","fromMe":false,"id":"3AAFE1A79B4EA1F1A554","participant":"","addressingMode":"pn"},"messageTimestamp":1771543402}],"nextPreKeyId":813,"firstUnuploadedPreKeyId":813,"accountSyncCounter":1,"accountSettings":{"unarchiveChats":true},"registered":false,"account":{"details":"CJeK8d4OEK+23swGGAkgACgA","accountSignatureKey":"pludAIgEOShgF2ib+2kRRUgiyZY3sQSkfxFDko5awRw=","accountSignature":"EenwzVVGPym42GjLTSBYgVrt0AIaphIZ5l6bXZSGyNG8PkHDcmYmH3xml+SWg9D8pw0FNgjGirYXhJswP5EMBg==","deviceSignature":"BWBpOLnMGTQgjrGQEGXG4gHLJ6ahW3N4MGsmBWvlwJdvuYkiErRXhUKQKhc5DmfAWHCpLEjdZldKQDQadRZxiw=="},"me":{"id":"557183158563:81@s.whatsapp.net","lid":"226615426568234:81@lid","name":"Daniel Levi"},"signalIdentities":[{"identifier":{"name":"226615426568234:81@lid","deviceId":0},"identifierKey":{"type":"Buffer","data":"BaZbnQCIBDkoYBdom/tpEUVIIsmWN7EEpH8RQ5KOWsEc"}}],"platform":"iphone","routingInfo":{"type":"Buffer","data":"CAUIDQgS"},"lastAccountSyncTimestamp":1771543349,"myAppStateKeyId":"AAAAAPL4","lastPropHash":"1K4hH4"}